ezprogress/__init__.py
ezprogress/progressbar.py
ezprogress-1.0.3.dist-info/DESCRIPTION.rst
ezprogress-1.0.3.dist-info/METADATA
ezprogress-1.0.3.dist-info/RECORD
ezprogress-1.0.3.dist-info/WHEEL
ezprogress-1.0.3.dist-info/metadata.json
ezprogress-1.0.3.dist-info/top_level.txt
