Metadata-Version: 2.0
Name: ezprogress
Version: 1.0.3
Summary: Simple, easy to use progress bar.
Home-page: https://github.com/Joklost/ezprogress
Author: Jonas Kloster Jacobsen
Author-email: joklost@gmail.com
License: MIT
Platform: UNKNOWN
Requires-Python: >=3.6
